nb_cli_fastapi/__init__.py
nb_cli_fastapi/feature.py
nb_cli_fastapi/main.py
cli_project_generator-0.1.0.dist-info/LICENSE
cli_project_generator-0.1.0.dist-info/METADATA
cli_project_generator-0.1.0.dist-info/WHEEL
cli_project_generator-0.1.0.dist-info/entry_points.txt
cli_project_generator-0.1.0.dist-info/top_level.txt
cli_project_generator-0.1.0.dist-info/RECORD
